evaluation/__init__.py
evaluation/ablation_runner.py
evaluation/baseline_strategies.py
evaluation/cache_manager.py
evaluation/cli_benchmark_client.py
evaluation/codex_cli_wrapper.py
evaluation/coding_metrics.py
evaluation/goal_tracking.py
evaluation/granular_constraint_metrics.py
evaluation/harness.py
evaluation/hierarchical_metrics.py
evaluation/llm_client.py
evaluation/locomo_eval.py
evaluation/metric_interfaces.py
evaluation/metrics.py
evaluation/multi_run_evaluator.py
evaluation/qa_metrics.py
evaluation/statistics.py
evaluation/strategy_comparison.py
evaluation/token_budget.py
evaluation/unified_aggregator.py
evaluation/unified_harness.py
evaluation/agents/__init__.py
evaluation/agents/amem_agent.py
evaluation/agents/base.py
evaluation/agents/codex_agent.py
evaluation/agents/compression_agent.py
evaluation/datasets/__init__.py
evaluation/datasets/base.py
evaluation/datasets/coding_dataset.py
evaluation/datasets/locomo_dataset.py
evaluation/datasets/template_dataset.py
instinct8_agent-0.4.6.dist-info/licenses/LICENSE
selective_salience/README.md
selective_salience/__init__.py
selective_salience/__main__.py
selective_salience/agent_cli.py
selective_salience/cli.py
selective_salience/codex_integration.py
selective_salience/compressor.py
selective_salience/instinct8_cli.py
selective_salience/ui.py
strategies/__init__.py
strategies/strategy_b_codex.py
strategies/strategy_base.py
strategies/strategy_d_amem.py
strategies/strategy_f_protected_core.py
strategies/strategy_g_hybrid.py
strategies/strategy_h_keyframe.py
strategies/strategy_h_selective_salience.py
strategies/strategy_i_hybrid_amem_protected.py
instinct8_agent-0.4.6.dist-info/METADATA
instinct8_agent-0.4.6.dist-info/WHEEL
instinct8_agent-0.4.6.dist-info/entry_points.txt
instinct8_agent-0.4.6.dist-info/top_level.txt
instinct8_agent-0.4.6.dist-info/RECORD
