Metadata-Version: 2.4
Name: instinct8-agent
Version: 0.4.6
Summary: Instinct8 Agent - Coding agent with Selective Salience Compression for better goal preservation
Author-email: Instinct8 <info@instinct8.ai>
License: Apache-2.0
Project-URL: Homepage, https://github.com/jjjorgenson/instinct8
Project-URL: Documentation, https://github.com/jjjorgenson/instinct8/blob/main/README.md
Project-URL: Repository, https://github.com/jjjorgenson/instinct8
Keywords: llm,compression,context,agents,salience,goal-preservation
Requires-Python: >=3.9
License-File: LICENSE
Requires-Dist: openai>=1.0.0
Requires-Dist: numpy>=1.24.0
Requires-Dist: sentence-transformers>=2.2.0
Requires-Dist: scikit-learn>=1.2.0
Requires-Dist: tiktoken>=0.5.0
Provides-Extra: dev
Requires-Dist: pytest>=7.0.0; extra == "dev"
Requires-Dist: pytest-asyncio>=0.21.0; extra == "dev"
Requires-Dist: mypy>=1.0.0; extra == "dev"
Dynamic: license-file
